ontwins/__init__.py
ontwins/demo.py
ontwins/core/gql.py
ontwins/core/keycloak.py
smu/__init__.py
smu/demo/rack.py
smu/prepare/co_settings.py
smu/prepare/orders.py
smu/util/api.py
smu/util/sheet.py
tools/__init__.py
tools/api.py
tools/co_settings.py
tools/orders.py
tools/py.typed
tools/rack.py
tools/sim_settings.py
smu_ontwins_demo-0.1.65.dist-info/METADATA
smu_ontwins_demo-0.1.65.dist-info/WHEEL
smu_ontwins_demo-0.1.65.dist-info/licenses/LICENSE
smu_ontwins_demo-0.1.65.dist-info/RECORD
