Metadata-Version: 2.4
Name: smu-ontwins-demo
Version: 0.1.65
Summary: Functions for SMU OnTwins demo package
Author-email: IGI Korea <customer@ontwins.com>
License-Expression: MIT
License-File: LICENSE
Classifier: Operating System :: OS Independent
Classifier: Programming Language :: Python :: 3
Classifier: Typing :: Typed
Requires-Python: >=3.9
Requires-Dist: gql[requests]
